luktianutl/__init__.py
luktianutl/descriptors.py
luktianutl/formular.py
luktianutl/imports.py
luktianutl/makeobj.py
luktianutl/nets.py
luktianutl/normalplot.py
luktianutl/preprocessing.py
luktianutl/readdata.py
luktianutl/sitesgens.py
luktianutl/sphere_exclusion.py
luktianutl/targets.py
luktianutl/utilies.py
luktianutl/validates.py
luktianutl-0.0.4.dist-info/METADATA
luktianutl-0.0.4.dist-info/WHEEL
luktianutl-0.0.4.dist-info/top_level.txt
luktianutl-0.0.4.dist-info/RECORD
