Metadata-Version: 2.1
Name: luktianutl
Version: 0.0.4
Summary: Utilities For Myself
Home-page: UNKNOWN
Author: luktian
Author-email: luktian@shu.edu.cn
Maintainer: luktian
Maintainer-email: luktian@shu.edu.cn
License: BSD License
Platform: all
Classifier: Development Status :: 4 - Beta
Classifier: Operating System :: OS Independent
Classifier: Intended Audience :: Developers
Classifier: License :: OSI Approved :: BSD License
Classifier: Programming Language :: Python
Classifier: Programming Language :: Python :: Implementation
Classifier: Programming Language :: Python :: 3.5
Classifier: Programming Language :: Python :: 3.6
Classifier: Topic :: Software Development :: Libraries
Requires-Dist: sklearn
Requires-Dist: numpy
Requires-Dist: pandas
Requires-Dist: scipy
